Metadata-Version: 2.1
Name: Dio-Images
Version: 0.0.1
Summary: projeto python leitura da imagem
Home-page: https://github.com/Theoldwine/package-template
Author: theoldwine
Author-email: sior@outlook.com
License: UNKNOWN
Platform: UNKNOWN
Requires-Python: >=3.8
Requires-Dist: matplotlib
Requires-Dist: numpy
Requires-Dist: scikit-image (>=0.16.1)
